README.md
setup.py
src/pm4edu/__init__.py
src/pm4edu.egg-info/PKG-INFO
src/pm4edu.egg-info/SOURCES.txt
src/pm4edu.egg-info/dependency_links.txt
src/pm4edu.egg-info/requires.txt
src/pm4edu.egg-info/top_level.txt