Metadata-Version: 1.0
Name: pm4edu
Version: 0
Summary: Python Package
Home-page: UNKNOWN
Author: UNKNOWN
Author-email: UNKNOWN
License: UNKNOWN
Platform: UNKNOWN
